Workbook

Sheet 前提条件
A1: 🐾 アズカル 収益モデル前提条件
A3: A. 取引単価（飼い主→シッター）
A4: 平均予約単価（1予約あたり） | B4: 10000 | C4: 円 | D4: 1泊×2泊が平均的な利用（@5,000円/泊 × 2泊）
A5: プラットフォーム手数料率 | B5: 0.15 | C5: （%） | D5: Rover=20%, DogHuggy=30%。競合より低い15%を訴求
A6: 1予約あたりプラットフォーム収益 | B6: =B4*B5 -> 1500 | C6: 円 | D6: =平均予約単価×手数料率（数式）
A7: 決済手数料（Stripe等） | B7: 0.031 | C7: （%） | D7: Stripe=3.1%（国内カード）
A8: 決済コスト控除後ネット収益/予約 | B8: =B6*(1-B7) -> 1453.5 | C8: 円 | D8: =収益 - 決済コスト
A9: B. 利用頻度・顧客生涯価値（LTV）
A10: 年間利用回数（飼い主1人あたり） | B10: 2.5 | C10: 回/年 | D10: 旅行・出張：年2〜3回が現実的な上限。ペットホテル比較参考値
A11: 年間チャーン率（離脱率） | B11: 0.3 | C11: 率 | D11: 定期利用は少なく離脱が早い想定。改善余地あり
A12: 平均顧客継続年数（=1/チャーン） | B12: =IFERROR(1/B11,0) -> 3.3333333 | C12: 年 | D12: =1÷年間チャーン率
A13: 顧客1人あたりLTV（粗利ベース） | B13: =B7*B10*B12 -> 0.25833333 | C13: 円 | D13: =ネット収益/予約×年間利用回数×継続年数
A14: C. 顧客獲得コスト（CAC）
A15: 飼い主CAC（オーガニック） | B15: 1500 | C15: 円 | D15: Instagram・口コミ・SEO等。人件費按分込み
A16: 飼い主CAC（有料広告） | B16: 5000 | C16: 円 | D16: SNS広告CPC×CTR×CVR試算。日本のアプリCAC相場3,000〜8,000円
A17: 飼い主ブレンドCAC（想定） | B17: 3000 | C17: 円 | D17: オーガニック60%＋有料40%の加重平均目安
A18: シッターCAC | B18: 2000 | C18: 円 | D18: SNS中心。需要側より獲得しやすい想定
A19: 両サイド合計CAC（1ペア獲得） | B19: =B17+B18 -> 5000 | C19: 円 | D19: =飼い主ブレンドcac＋シッターCAC
A20: LTV/CAC倍率（飼い主のみ） | B20: =IFERROR(B13/B17,0) -> 8.6111111e-05 | C20: 倍 | D20: =飼い主ltv÷飼い主ブレンドCAC。3倍以上が健全ライン
A21: D. 月次固定費（ベースライン）
A22: エンジニア人件費（Claude対応・実質0） | B22: 0 | C22: 円/月 | D22: Claude活用により人件費ゼロ。サービス利用料のみ（インフラ費に含む）
A23: マーケ担当人件費（妻が担当・実質0） | B23: 0 | C23: 円/月 | D23: 創業メンバーが兼任。外注費が発生した場合のみ別途計上
A24: インフラ・SaaS費用 | B24: 7000 | C24: 円/月 | D24: Vercel Pro約3,000円 + Supabase Pro約3,700円 + ドメイン等。Claude API・Notionは個人兼用のため除外
A25: 法務・会計費用（規約整備まで不要） | B25: 0 | C25: 円/月 | D25: 規約作成は初期に単発対応。顧問契約は結ばない方針
A26: その他雑費 | B26: 8000 | C26: 円/月 | D26: 通信費按分 + Figma/Notion等ツール。できる限り無料枠で運用
A27: 月次固定費合計 | B27: =SUM(B22:B26) -> 15000 | C27: 円/月 | D27: =合計
A28: 年間固定費合計 | B28: =B27*12 -> 180000 | C28: 円/年 | D28: =月次×12
A29: E. ユーザー成長・マーケティング予算仮定
A30: 初年度末アクティブ飼い主数（ベース・広告なし） | B30: 300 | C30: 人 | D30: 先行登録50〜100件から口コミ・Instagram有機流入のみ。300人が現実的な目標
A31: 年間成長率（Y1→Y2） | B31: 1.3 | C31: 倍 | D31: Y1→Y2：Instagram・口コミ主体。広告なしで30%増が現実的上限
A32: 年間成長率（Y2→Y3） | B32: 1.5 | C32: 倍 | D32: Y2→Y3：プロダクト成熟、紹介フライホイールが回り始める
A33: 年間成長率（Y3→Y4） | B33: 1.5 | C33: 倍 | D33: Y3→Y4：継続伸長
A34: 年間成長率（Y4→Y5） | B34: 1.3 | C34: 倍 | D34: Y4→Y5：安定フェーズ。大型成長は資金調達後
A35: 月次広告予算（上限・ブートストラップ） | B35: 30000 | C35: 円/月 | D35: Instagram少額広告＋ツール代のみ。資金調達後に拡大予定
A37: 【凡例】 青文字 = 変更可能な入力値（仮定） ｜ 黒文字 = 数式（自動計算） ｜ 黄背景 = 特に要確認の重要仮定

Sheet ユニットエコノミクス
A1: 🔍 ユニットエコノミクス分析（飼い主1人あたり）
A3: ▍ LTV構成ウォーターフォール
A4: ① 平均予約単価 | B4: =前提条件!B4 -> 10000
A5: ② プラットフォーム手数料率 | B5: =前提条件!B5 -> 0.15
A6: ③ 手数料収益/予約 | B6: =前提条件!B6 -> 1500
A7: ④ 決済コスト率（Stripe） | B7: =前提条件!B7 -> 0.031
A8: ⑤ 決済コスト控除後収益/予約 | B8: =前提条件!B7 -> 0.031 | C8: 実質手取り収益。Stripeコスト=予約単価×3.1%
A9: ⑥ 年間利用回数 | B9: =前提条件!B10 -> 2.5
A10: ⑦ 年間収益/ユーザー | B10: =B8*B9 -> 0.0775 | C10: ③×⑥
A11: ⑧ 年間チャーン率 | B11: =前提条件!B11 -> 0.3
A12: ⑨ 平均継続年数 | B12: =前提条件!B12 -> 3.3333333
A13: ⑩ 飼い主LTV（累計収益） | B13: =B10*B12 -> 0.25833333 | C13: =⑦ × ⑨。これがCAC上限の理論値
A15: ▍ 顧客獲得コスト（CAC）と回収期間
A16: 飼い主ブレンドCAC | B16: =前提条件!B17 -> 3000
A17: シッターCAC | B17: =前提条件!B18 -> 2000
A18: 両サイド合計CAC | B18: =前提条件!B19 -> 5000
A19: LTV / CAC倍率（飼い主のみ） | B19: =IFERROR(B13/B16,0) -> 8.6111111e-05 | C19: ⚠️ 3倍以上が健全ライン。2倍以下は危険域
A20: CAC回収期間（月数） | B20: =IFERROR(B16/B10*12,0) -> 464516.13 | C20: ⚠️ 12ヶ月以内が理想。長いほどキャッシュ消費が大きい
A21: 損益分岐点（年間予約数/ユーザー） | B21: =IFERROR(B16/B8,0) -> 96774.194 | C21: このN回以上使えばCAC回収。ビジネス成立の下限
A23: ▍ 構造的課題の整理
A24: 課題①：低頻度利用 | B24: 年2〜3回の予約では年間収益は4,000〜5,000円/ユーザーにとどまる。LTVを上げるにはリピート促進・単価向上が必要
A25: 課題②：CAC vs LTV | B25: LTV/CACが3倍を下回る場合、広告を拡大するほど赤字が拡大する。オーガニック獲得比率が鍵
A26: 課題③：両サイド問題 | B26: マーケットプレイスは飼い主・シッター両方を獲得する必要があり実質CACは2倍。初期資本効率が悪化しやすい
A27: 課題④：スイッチングコスト | B27: 飼い主とシッターが直接連絡を取り始めると離脱する。関係性を保つ機能（レポート・保険・レビュー）が重要

Sheet 収益・損益試算
A1: 📊 収益・損益試算（5ヶ年） 単位：万円
A2: 指標 | B2: Year 1 | C2: Year 2 | D2: Year 3 | E2: Year 4 | F2: Year 5
A3: ▍ ユーザー規模
A4: アクティブ飼い主数（人） | B4: =前提条件!B30 -> 300 | C4: =B4*前提条件!B31 -> 390 | D4: =C4*前提条件!B32 -> 585 | E4: =D4*前提条件!B33 -> 877.5 | F4: =E4*前提条件!B34 -> 1140.75
A5: 登録シッター数（人） | B5: =ROUND(B4/3,0) -> 100 | C5: =ROUND(C4/3,0) -> 130 | D5: =ROUND(D4/3,0) -> 195 | E5: =ROUND(E4/3,0) -> 293 | F5: =ROUND(F4/3,0) -> 380
A6: 年間総予約件数 | B6: =B4*前提条件!$B$10 -> 750 | C6: =C4*前提条件!$B$10 -> 975 | D6: =D4*前提条件!$B$10 -> 1462.5 | E6: =E4*前提条件!$B$10 -> 2193.75 | F6: =F4*前提条件!$B$10 -> 2851.875
A7: ▍ GMV・プラットフォーム収益
A8: GMV（流通総額）（万円） | B8: =B6*前提条件!$B$4/10000 -> 750 | C8: =C6*前提条件!$B$4/10000 -> 975 | D8: =D6*前提条件!$B$4/10000 -> 1462.5 | E8: =E6*前提条件!$B$4/10000 -> 2193.75 | F8: =F6*前提条件!$B$4/10000 -> 2851.875
A9: プラットフォーム収益（万円） | B9: =B8*前提条件!$B$5 -> 112.5 | C9: =C8*前提条件!$B$5 -> 146.25 | D9: =D8*前提条件!$B$5 -> 219.375 | E9: =E8*前提条件!$B$5 -> 329.0625 | F9: =F8*前提条件!$B$5 -> 427.78125
A10: 決済コスト（万円） | B10: =-B8*前提条件!$B$7 -> -23.25 | C10: =-C8*前提条件!$B$7 -> -30.225 | D10: =-D8*前提条件!$B$7 -> -45.3375 | E10: =-E8*前提条件!$B$7 -> -68.00625 | F10: =-F8*前提条件!$B$7 -> -88.408125
A11: ネット収益（万円） | B11: =B9+B10 -> 89.25 | C11: =C9+C10 -> 116.025 | D11: =D9+D10 -> 174.0375 | E11: =E9+E10 -> 261.05625 | F11: =F9+F10 -> 339.37313
A12: ▍ コスト
A13: 広告費（万円）・月次固定上限 | B13: =-前提条件!$B$35*12/10000 -> -36 | C13: =-前提条件!$B$35*12/10000 -> -36 | D13: =-前提条件!$B$35*12/10000 -> -36 | E13: =-前提条件!$B$35*12/10000 -> -36 | F13: =-前提条件!$B$35*12/10000 -> -36
A14: 固定費（万円） | B14: =-前提条件!$B$28/10000 -> -18 | C14: =-前提条件!$B$28/10000 -> -18 | D14: =-前提条件!$B$28/10000 -> -18 | E14: =-前提条件!$B$28/10000 -> -18 | F14: =-前提条件!$B$28/10000 -> -18
A15: 総コスト（万円） | B15: =B13+B14 -> -54 | C15: =C13+C14 -> -54 | D15: =D13+D14 -> -54 | E15: =E13+E14 -> -54 | F15: =F13+F14 -> -54
A16: ▍ 損益
A17: 営業利益（EBITDA近似）（万円） | B17: =B11+B15 -> 35.25 | C17: =C11+C15 -> 62.025 | D17: =D11+D15 -> 120.0375 | E17: =E11+E15 -> 207.05625 | F17: =F11+F15 -> 285.37313
A18: 利益率（%） | B18: =IFERROR(B17/B11,0) -> 0.39495798 | C18: =IFERROR(C17/C11,0) -> 0.53458306 | D18: =IFERROR(D17/D11,0) -> 0.68972204 | E18: =IFERROR(E17/E11,0) -> 0.79314803 | F18: =IFERROR(F17/F11,0) -> 0.8408831
A19: 累積損益（万円） | B19: =B17 -> 35.25 | C19: =B19+C17 -> 97.275 | D19: =C19+D17 -> 217.3125 | E19: =D19+E17 -> 424.36875 | F19: =E19+F17 -> 709.74188
A21: ※ 黄色セルは前提条件シートの変更可能な仮定が直接影響する。前提条件のユーザー数・成長率・CAC等を変えると自動更新されます。

Sheet シナリオ分析
A1: 🎯 シナリオ分析（Year 5時点） 単位：万円
A2: 指標 | B2: 悲観シナリオ | C2: ベースシナリオ | D2: 楽観シナリオ | E2: 備考
A3: ▍ シナリオ別前提（Y5時点）
A4: Y5 アクティブ飼い主数（人） | B4: 3000 | C4: 20000 | D4: 80000 | E4: 悲：成長鈍化 ベース：順調 楽：口コミ爆発
A5: 年間利用回数/人 | B5: 1.5 | C5: 2.5 | D5: 4 | E5: 悲：旅行自粛 ベース：標準 楽：デイケア等追加
A6: 平均予約単価（円） | B6: 8000 | C6: 10000 | D6: 13000 | E6: 悲：値下げ圧力 楽：プレミアム化
A7: 手数料率 | B7: 0.12 | C7: 0.15 | D7: 0.18 | E7: 悲：競争激化で低下 楽：値上げ成功
A8: ブレンドCAC（円） | B8: 4000 | C8: 1500 | D8: 800 | E8: 悲：広告依存 ベース：均衡 楽：有機成長
A9: ▍ Y5 試算結果
A10: GMV（万円） | B10: =B4*B5*B6/10000 -> 3600 | C10: =C4*C5*C6/10000 -> 50000 | D10: =D4*D5*D6/10000 -> 416000
A11: プラットフォーム収益（万円） | B11: =B10*B7 -> 432 | C11: =C10*C7 -> 7500 | D11: =D10*D7 -> 74880
A12: 決済コスト控除後収益（万円） | B12: =B11*(1-前提条件!$B$7) -> 418.608 | C12: =C11*(1-前提条件!$B$7) -> 7267.5 | D12: =D11*(1-前提条件!$B$7) -> 72558.72
A13: 固定費（万円） | B13: =-前提条件!$B$28/10000 -> -18 | C13: =-前提条件!$B$28/10000 -> -18 | D13: =-前提条件!$B$28/10000 -> -18
A14: マーケ費（万円） | B14: =-前提条件!$B$35*12/10000 -> -36 | C14: =-前提条件!$B$35*12/10000 -> -36 | D14: =-前提条件!$B$35*12/10000 -> -36
A15: EBITDA（万円） | B15: =B12+B13+B14 -> 364.608 | C15: =C12+C13+C14 -> 7213.5 | D15: =D12+D13+D14 -> 72504.72
A16: EBITDA margin | B16: =IFERROR(B15/B12,0) -> 0.87100103 | C16: =IFERROR(C15/C12,0) -> 0.99256966 | D16: =IFERROR(D15/D12,0) -> 0.99925578
A17: LTV/CAC倍率 | B17: =IFERROR((B12/(B4*前提条件!$B$12))*前提条件!$B$10*前提条件!$B$12/B8,0) -> 8.721e-05 | C17: =IFERROR((C12/(C4*前提条件!$B$12))*前提条件!$B$10*前提条件!$B$12/C8,0) -> 0.000605625 | D17: =IFERROR((D12/(D4*前提条件!$B$12))*前提条件!$B$10*前提条件!$B$12/D8,0) -> 0.002834325
A19: ▍ シナリオ解説・戦略示唆
A20: 悲観シナリオ | B20: 広告なしでの成長が期待を下回り、Y5でも飼い主3,000人にとどまる。 固定費は低いため単月赤字にはならないが、スケールせず事業継続の意義が薄れる。 ピボットかSNS戦略の抜本見直しが必要。
A21: ベースシナリオ | B21: Instagram・口コミのフライホイールが機能し、Y5で飼い主2万人。 広告費は月3万円固定のまま、LTV/CAC改善でY2から累積黒字化。 Y3〜Y4に余剰キャッシュが貯まり、そこで初めて広告投資 or 資金調達の選択肢が生まれる。
A22: 楽観シナリオ | B22: ペットオーナーのバイラル紹介が連鎖し、CAC実質800円以下を実現。 広告費ほぼゼロのまま8万人獲得。Y5 EBITDA数千万円レベル。 「広告なし＝低CAC」の構造が最大限に機能したケース。
A23: 共通の注意点 | B23: 広告非依存モデルの最大リスクは「成長速度のコントロール不能」。 遅すぎると競合に先行される可能性がある。Y2〜Y3の累積キャッシュを見ながら 月3万→10万→30万と段階的に広告予算を引き上げる戦略が現実的。
